demo.py
yapydi/__init__.py
yapydi/lib.py
yapydi-0.1.3.dist-info/LICENSE
yapydi-0.1.3.dist-info/METADATA
yapydi-0.1.3.dist-info/WHEEL
yapydi-0.1.3.dist-info/top_level.txt
yapydi-0.1.3.dist-info/RECORD
