Metadata-Version: 2.1
Name: yapydi
Version: 0.1.3
Summary: Yet Another Python Dependency Injection
Author-email: Kaiping Zou <zoukaiping@gmail.com>
Project-URL: Homepage, https://github.com/ColinZou/yapydi
Project-URL: Source Code, https://github.com/ColinZou/yapydi
Classifier: Programming Language :: Python :: 3
Classifier: License :: OSI Approved :: GNU General Public License v3 (GPLv3)
Classifier: Operating System :: OS Independent
Requires-Python: >=3.10
License-File: LICENSE
